dawg_python/__init__.py
dawg_python/dawgs.py
dawg_python/units.py
dawg_python/wrapper.py
dawg2_python-0.8.1.dist-info/LICENSE
dawg2_python-0.8.1.dist-info/METADATA
dawg2_python-0.8.1.dist-info/WHEEL
dawg2_python-0.8.1.dist-info/RECORD
