Metadata-Version: 2.1
Name: DAWG2-Python
Version: 0.8.1
Summary: Pure-python reader for DAWGs (DAFSAs) created by dawgdic C++ library or DAWG Python extension.
Home-page: https://github.com/pymorphy2-fork/DAWG-Python/
License: MIT
Author: Mikhail Korobov
Author-email: kmike84@gmail.com
Requires-Python: >=3.8,<4.0
Classifier: Development Status :: 4 - Beta
Classifier: Intended Audience :: Developers
Classifier: Intended Audience :: Science/Research
Classifier: License :: OSI Approved :: MIT License
Classifier: Programming Language :: Python
Classifier: Programming Language :: Python :: 3
Classifier: Programming Language :: Python :: 3.8
Classifier: Programming Language :: Python :: 3.9
Classifier: Programming Language :: Python :: 3.10
Classifier: Programming Language :: Python :: 3.11
Classifier: Programming Language :: Python :: 3.12
Classifier: Programming Language :: Python :: Implementation :: CPython
Classifier: Programming Language :: Python :: Implementation :: PyPy
Classifier: Topic :: Scientific/Engineering :: Information Analysis
Classifier: Topic :: Software Development :: Libraries :: Python Modules
Classifier: Topic :: Text Processing :: Linguistic
Project-URL: Repository, https://github.com/pymorphy2-fork/DAWG-Python/
